MANIFEST.in
README.md
VERSION.txt
requirements.txt
setup.py
balloon_block_editor/__init__.py
balloon_block_editor/fields.py
balloon_block_editor.egg-info/PKG-INFO
balloon_block_editor.egg-info/SOURCES.txt
balloon_block_editor.egg-info/dependency_links.txt
balloon_block_editor.egg-info/not-zip-safe
balloon_block_editor.egg-info/top_level.txt
core/__init__.py
core/admin.py
core/asgi.py
core/models.py
core/settings.py
core/urls.py
core/wsgi.py
core/migrations/0001_initial.py
core/migrations/0002_auto_20200911_0510.py
core/migrations/0003_auto_20200911_0513.py
core/migrations/__init__.py